dvtv_dl/__init__.py
dvtv_dl/__main__.py
dvtv_dl-0.1.1.dist-info/entry_points.txt
dvtv_dl-0.1.1.dist-info/WHEEL
dvtv_dl-0.1.1.dist-info/METADATA
dvtv_dl-0.1.1.dist-info/RECORD
